MANIFEST.in
README.md
setup.py
hlnsync.egg-info/PKG-INFO
hlnsync.egg-info/SOURCES.txt
hlnsync.egg-info/dependency_links.txt
hlnsync.egg-info/entry_points.txt
hlnsync.egg-info/requires.txt
hlnsync.egg-info/top_level.txt
lnsync_pkg/__init__.py
lnsync_pkg/argparse_config.py
lnsync_pkg/argparse_scoped.py
lnsync_pkg/backtracker.py
lnsync_pkg/fdupes.py
lnsync_pkg/filehashtree.py
lnsync_pkg/fileproptree.py
lnsync_pkg/filesystems.py
lnsync_pkg/filetree.py
lnsync_pkg/freedesktop_thumbnailer.py
lnsync_pkg/glob_matcher.py
lnsync_pkg/gnome_thumbnailer.py
lnsync_pkg/groupedfileprinter.py
lnsync_pkg/hasher_functions.py
lnsync_pkg/human2bytes.py
lnsync_pkg/image_dhash.py
lnsync_pkg/lnsync.py
lnsync_pkg/lnsync_api.py
lnsync_pkg/lnsync_cmd_handlers.py
lnsync_pkg/lnsync_treeargs.py
lnsync_pkg/matcher.py
lnsync_pkg/metadata.py
lnsync_pkg/miscutils.py
lnsync_pkg/modaltype.py
lnsync_pkg/onegraph.py
lnsync_pkg/prefixdbname.py
lnsync_pkg/printutils.py
lnsync_pkg/propdbmanager.py
lnsync_pkg/sqlpropdb.py
lnsync_pkg/thread_utils.py
random_pkg/__init__.py
random_pkg/random_extras.py
random_pkg/random_tree.py