Metadata-Version: 2.1
Name: hlnsync
Version: 0.9.0
Summary: Sync local dirs by content, with rename detection and hard link support, plus fast fdupes, and more.
Home-page: https://github.com/mrsimoes/hlnsync
Author: Miguel Simoes
Author-email: miguelrsimoes@yahoo.com
License: GNU General Public License v3
Download-URL: https://github.com/mrsimoes/hlnsync/archive/v0.9.0.tar.gz
Keywords: sync rsync fast rename backup link hardlink fdupes
Platform: UNKNOWN
Classifier: Development Status :: 3 - Alpha
Classifier: Environment :: Console
Classifier: Operating System :: POSIX :: Linux
Classifier: Programming Language :: Python
Classifier: Programming Language :: Python :: 3 :: Only
Classifier: Programming Language :: Python :: 3.6
Classifier: Programming Language :: Python :: 3.7
Classifier: Programming Language :: Python :: 3.8
Classifier: License :: OSI Approved :: GNU General Public License v3 (GPLv3)
Classifier: Topic :: System :: Archiving :: Backup
Classifier: Topic :: System :: Archiving :: Mirroring
Classifier: Topic :: Utilities
